{"time":{"updated":"Oct 16, 2024 07:28:16 UTC","updatedISO":"2024-10-16T07:28:16+00:00","updateduk":"Oct 16, 2024 at 08:28 BST"},"disclaimer":"This data was produced from the CoinDesk Bitcoin Price Index (USD). Non-USD currency data converted using hourly conversion rate from openexchangerates.org","chartName":"Bitcoin","bpi":{"USD":{"code":"USD","symbol":"&#36;","rate":"66,858.616","description":"United States Dollar","rate_float":66858.6161},"GBP":{"code":"GBP","symbol":"&pound;","rate":"51,474.917","description":"British Pound Sterling","rate_float":51474.9166},"EUR":{"code":"EUR","symbol":"&euro;","rate":"61,464.262","description":"Euro","rate_float":61464.2624},"CNY":{"code":"CNY","symbol":"&yen;","rate":"475,933.059","description":"Chinese Yuan","rate_float":475933.0589}}}