{"time":{"updated":"Oct 7, 2024 14:48:33 UTC","updatedISO":"2024-10-07T14:48:33+00:00","updateduk":"Oct 7, 2024 at 15:48 BST"},"disclaimer":"This data was produced from the CoinDesk Bitcoin Price Index (USD). Non-USD currency data converted using hourly conversion rate from openexchangerates.org","chartName":"Bitcoin","bpi":{"USD":{"code":"USD","symbol":"&#36;","rate":"64,029.882","description":"United States Dollar","rate_float":64029.8815},"GBP":{"code":"GBP","symbol":"&pound;","rate":"48,980.618","description":"British Pound Sterling","rate_float":48980.6183},"EUR":{"code":"EUR","symbol":"&euro;","rate":"58,316.047","description":"Euro","rate_float":58316.0469},"CNY":{"code":"CNY","symbol":"&yen;","rate":"449,464.156","description":"Chinese Yuan","rate_float":449464.1559}}}