{"time":{"updated":"Sep 7, 2024 02:45:13 UTC","updatedISO":"2024-09-07T02:45:13+00:00","updateduk":"Sep 7, 2024 at 03:45 BST"},"disclaimer":"This data was produced from the CoinDesk Bitcoin Price Index (USD). Non-USD currency data converted using hourly conversion rate from openexchangerates.org","chartName":"Bitcoin","bpi":{"USD":{"code":"USD","symbol":"&#36;","rate":"53,936.2","description":"United States Dollar","rate_float":53936.1995},"GBP":{"code":"GBP","symbol":"&pound;","rate":"41,072.362","description":"British Pound Sterling","rate_float":41072.362},"EUR":{"code":"EUR","symbol":"&euro;","rate":"48,634.271","description":"Euro","rate_float":48634.2711},"CNY":{"code":"CNY","symbol":"&yen;","rate":"382,348.325","description":"Chinese Yuan","rate_float":382348.3247}}}