{"time":{"updated":"Apr 7, 2024 16:51:06 UTC","updatedISO":"2024-04-07T16:51:06+00:00","updateduk":"Apr 7, 2024 at 17:51 BST"},"disclaimer":"This data was produced from the CoinDesk Bitcoin Price Index (USD). Non-USD currency data converted using hourly conversion rate from openexchangerates.org","chartName":"Bitcoin","bpi":{"USD":{"code":"USD","symbol":"&#36;","rate":"70,298.281","description":"United States Dollar","rate_float":70298.2805},"GBP":{"code":"GBP","symbol":"&pound;","rate":"55,624.499","description":"British Pound Sterling","rate_float":55624.4987},"EUR":{"code":"EUR","symbol":"&euro;","rate":"64,797.51","description":"Euro","rate_float":64797.5104},"CNY":{"code":"CNY","symbol":"&yen;","rate":"508,425.284","description":"Chinese Yuan","rate_float":508425.2842}}}