{"time":{"updated":"Aug 2, 2022 06:35:00 UTC","updatedISO":"2022-08-02T06:35:00+00:00","updateduk":"Aug 2, 2022 at 07:35 BST"},"disclaimer":"This data was produced from the CoinDesk Bitcoin Price Index (USD). Non-USD currency data converted using hourly conversion rate from openexchangerates.org","chartName":"Bitcoin","bpi":{"USD":{"code":"USD","symbol":"&#36;","rate":"22,931.9377","description":"United States Dollar","rate_float":22931.9377},"GBP":{"code":"GBP","symbol":"&pound;","rate":"19,161.7436","description":"British Pound Sterling","rate_float":19161.7436},"EUR":{"code":"EUR","symbol":"&euro;","rate":"22,339.0553","description":"Euro","rate_float":22339.0553},"CNY":{"code":"CNY","symbol":"&yen;","rate":"40,202.5000","description":"Chinese Yuan","rate_float":40202.5}}}