{"time":{"updated":"Jun 12, 2024 09:38:01 UTC","updatedISO":"2024-06-12T09:38:01+00:00","updateduk":"Jun 12, 2024 at 10:38 BST"},"disclaimer":"This data was produced from the CoinDesk Bitcoin Price Index (USD). Non-USD currency data converted using hourly conversion rate from openexchangerates.org","chartName":"Bitcoin","bpi":{"USD":{"code":"USD","symbol":"&#36;","rate":"67,508.257","description":"United States Dollar","rate_float":67508.2574},"GBP":{"code":"GBP","symbol":"&pound;","rate":"52,916.213","description":"British Pound Sterling","rate_float":52916.2126},"EUR":{"code":"EUR","symbol":"&euro;","rate":"62,818.121","description":"Euro","rate_float":62818.1212},"CNY":{"code":"CNY","symbol":"&yen;","rate":"479,801.438","description":"Chinese Yuan","rate_float":479801.4379}}}