{"time":{"updated":"Nov 26, 2024 04:38:31 UTC","updatedISO":"2024-11-26T04:38:31+00:00","updateduk":"Nov 26, 2024 at 04:38 GMT"},"disclaimer":"This data was produced from the CoinDesk Bitcoin Price Index (USD). Non-USD currency data converted using hourly conversion rate from openexchangerates.org","chartName":"Bitcoin","bpi":{"USD":{"code":"USD","symbol":"&#36;","rate":"94,436.33","description":"United States Dollar","rate_float":94436.3298},"GBP":{"code":"GBP","symbol":"&pound;","rate":"75,258.483","description":"British Pound Sterling","rate_float":75258.4832},"EUR":{"code":"EUR","symbol":"&euro;","rate":"90,128.239","description":"Euro","rate_float":90128.2388},"CNY":{"code":"CNY","symbol":"&yen;","rate":"684,262.037","description":"Chinese Yuan","rate_float":684262.0365}}}