{"time":{"updated":"Jul 8, 2024 05:37:19 UTC","updatedISO":"2024-07-08T05:37:19+00:00","updateduk":"Jul 8, 2024 at 06:37 BST"},"disclaimer":"This data was produced from the CoinDesk Bitcoin Price Index (USD). Non-USD currency data converted using hourly conversion rate from openexchangerates.org","chartName":"Bitcoin","bpi":{"USD":{"code":"USD","symbol":"&#36;","rate":"55,381.476","description":"United States Dollar","rate_float":55381.476},"GBP":{"code":"GBP","symbol":"&pound;","rate":"43,217.932","description":"British Pound Sterling","rate_float":43217.9316},"EUR":{"code":"EUR","symbol":"&euro;","rate":"51,142.91","description":"Euro","rate_float":51142.9101},"CNY":{"code":"CNY","symbol":"&yen;","rate":"402,573.487","description":"Chinese Yuan","rate_float":402573.487}}}