{"time":{"updated":"Aug 6, 2024 22:47:36 UTC","updatedISO":"2024-08-06T22:47:36+00:00","updateduk":"Aug 6, 2024 at 23:47 BST"},"disclaimer":"This data was produced from the CoinDesk Bitcoin Price Index (USD). Non-USD currency data converted using hourly conversion rate from openexchangerates.org","chartName":"Bitcoin","bpi":{"USD":{"code":"USD","symbol":"&#36;","rate":"56,388.313","description":"United States Dollar","rate_float":56388.3128},"GBP":{"code":"GBP","symbol":"&pound;","rate":"44,430.382","description":"British Pound Sterling","rate_float":44430.3816},"EUR":{"code":"EUR","symbol":"&euro;","rate":"51,594.066","description":"Euro","rate_float":51594.0657},"CNY":{"code":"CNY","symbol":"&yen;","rate":"402,062.768","description":"Chinese Yuan","rate_float":402062.7675}}}