{"time":{"updated":"Apr 15, 2024 09:44:12 UTC","updatedISO":"2024-04-15T09:44:12+00:00","updateduk":"Apr 15, 2024 at 10:44 BST"},"disclaimer":"This data was produced from the CoinDesk Bitcoin Price Index (USD). Non-USD currency data converted using hourly conversion rate from openexchangerates.org","chartName":"Bitcoin","bpi":{"USD":{"code":"USD","symbol":"&#36;","rate":"66,940.916","description":"United States Dollar","rate_float":66940.9162},"GBP":{"code":"GBP","symbol":"&pound;","rate":"53,631.255","description":"British Pound Sterling","rate_float":53631.2546},"EUR":{"code":"EUR","symbol":"&euro;","rate":"62,817.356","description":"Euro","rate_float":62817.3557},"CNY":{"code":"CNY","symbol":"&yen;","rate":"484,551.822","description":"Chinese Yuan","rate_float":484551.8216}}}