{"time":{"updated":"Jun 27, 2023 09:08:00 UTC","updatedISO":"2023-06-27T09:08:00+00:00","updateduk":"Jun 27, 2023 at 10:08 BST"},"disclaimer":"This data was produced from the CoinDesk Bitcoin Price Index (USD). Non-USD currency data converted using hourly conversion rate from openexchangerates.org","chartName":"Bitcoin","bpi":{"USD":{"code":"USD","symbol":"&#36;","rate":"30,356.3057","description":"United States Dollar","rate_float":30356.3057},"GBP":{"code":"GBP","symbol":"&pound;","rate":"25,365.4862","description":"British Pound Sterling","rate_float":25365.4862},"EUR":{"code":"EUR","symbol":"&euro;","rate":"29,571.4738","description":"Euro","rate_float":29571.4738},"CNY":{"code":"CNY","symbol":"&yen;","rate":"40,202.5000","description":"Chinese Yuan","rate_float":40202.5}}}