{"time":{"updated":"Jun 28, 2024 00:42:18 UTC","updatedISO":"2024-06-28T00:42:18+00:00","updateduk":"Jun 28, 2024 at 01:42 BST"},"disclaimer":"This data was produced from the CoinDesk Bitcoin Price Index (USD). Non-USD currency data converted using hourly conversion rate from openexchangerates.org","chartName":"Bitcoin","bpi":{"USD":{"code":"USD","symbol":"&#36;","rate":"61,514.209","description":"United States Dollar","rate_float":61514.2087},"GBP":{"code":"GBP","symbol":"&pound;","rate":"48,648.697","description":"British Pound Sterling","rate_float":48648.6965},"EUR":{"code":"EUR","symbol":"&euro;","rate":"57,447.812","description":"Euro","rate_float":57447.812},"CNY":{"code":"CNY","symbol":"&yen;","rate":"447,097.572","description":"Chinese Yuan","rate_float":447097.5719}}}