{"time":{"updated":"Nov 18, 2021 20:34:00 UTC","updatedISO":"2021-11-18T20:34:00+00:00","updateduk":"Nov 18, 2021 at 20:34 GMT"},"disclaimer":"This data was produced from the CoinDesk Bitcoin Price Index (USD). Non-USD currency data converted using hourly conversion rate from openexchangerates.org","chartName":"Bitcoin","bpi":{"USD":{"code":"USD","symbol":"&#36;","rate":"57,972.0870","description":"United States Dollar","rate_float":57972.087},"GBP":{"code":"GBP","symbol":"&pound;","rate":"42,952.3309","description":"British Pound Sterling","rate_float":42952.3309},"EUR":{"code":"EUR","symbol":"&euro;","rate":"50,984.1896","description":"Euro","rate_float":50984.1896},"CNY":{"code":"CNY","symbol":"&yen;","rate":"40,202.5000","description":"Chinese Yuan","rate_float":40202.5}}}