{"time":{"updated":"Sep 10, 2021 04:56:00 UTC","updatedISO":"2021-09-10T04:56:00+00:00","updateduk":"Sep 10, 2021 at 05:56 BST"},"disclaimer":"This data was produced from the CoinDesk Bitcoin Price Index (USD). Non-USD currency data converted using hourly conversion rate from openexchangerates.org","chartName":"Bitcoin","bpi":{"USD":{"code":"USD","symbol":"&#36;","rate":"46,650.9111","description":"United States Dollar","rate_float":46650.9111},"GBP":{"code":"GBP","symbol":"&pound;","rate":"33,679.2987","description":"British Pound Sterling","rate_float":33679.2987},"EUR":{"code":"EUR","symbol":"&euro;","rate":"39,433.5487","description":"Euro","rate_float":39433.5487},"CNY":{"code":"CNY","symbol":"&yen;","rate":"40,202.5000","description":"Chinese Yuan","rate_float":40202.5}}}