{"time":{"updated":"Dec 30, 2024 20:15:44 UTC","updatedISO":"2024-12-30T20:15:44+00:00","updateduk":"Dec 30, 2024 at 20:15 GMT"},"disclaimer":"This data was produced from the CoinDesk Bitcoin Price Index (USD). Non-USD currency data converted using hourly conversion rate from openexchangerates.org","chartName":"Bitcoin","bpi":{"USD":{"code":"USD","symbol":"&#36;","rate":"94,906.427","description":"United States Dollar","rate_float":94906.4273},"GBP":{"code":"GBP","symbol":"&pound;","rate":"75,685.978","description":"British Pound Sterling","rate_float":75685.9776},"EUR":{"code":"EUR","symbol":"&euro;","rate":"91,050.474","description":"Euro","rate_float":91050.4741},"CNY":{"code":"CNY","symbol":"&yen;","rate":"692,684.05","description":"Chinese Yuan","rate_float":692684.0502}}}