{"time":{"updated":"Feb 10, 2024 20:31:58 UTC","updatedISO":"2024-02-10T20:31:58+00:00","updateduk":"Feb 10, 2024 at 20:31 GMT"},"disclaimer":"This data was produced from the CoinDesk Bitcoin Price Index (USD). Non-USD currency data converted using hourly conversion rate from openexchangerates.org","chartName":"Bitcoin","bpi":{"USD":{"code":"USD","symbol":"&#36;","rate":"47,544.978","description":"United States Dollar","rate_float":47544.9778},"GBP":{"code":"GBP","symbol":"&pound;","rate":"37,647.445","description":"British Pound Sterling","rate_float":37647.4446},"EUR":{"code":"EUR","symbol":"&euro;","rate":"44,086.081","description":"Euro","rate_float":44086.0806},"CNY":{"code":"CNY","symbol":"&yen;","rate":"338,624.841","description":"Chinese Yuan","rate_float":338624.8406}}}