{"time":{"updated":"Sep 8, 2024 13:49:23 UTC","updatedISO":"2024-09-08T13:49:23+00:00","updateduk":"Sep 8, 2024 at 14:49 BST"},"disclaimer":"This data was produced from the CoinDesk Bitcoin Price Index (USD). Non-USD currency data converted using hourly conversion rate from openexchangerates.org","chartName":"Bitcoin","bpi":{"USD":{"code":"USD","symbol":"&#36;","rate":"54,375.291","description":"United States Dollar","rate_float":54375.2907},"GBP":{"code":"GBP","symbol":"&pound;","rate":"41,408.306","description":"British Pound Sterling","rate_float":41408.3064},"EUR":{"code":"EUR","symbol":"&euro;","rate":"49,030.2","description":"Euro","rate_float":49030.1996},"CNY":{"code":"CNY","symbol":"&yen;","rate":"385,460.998","description":"Chinese Yuan","rate_float":385460.9983}}}