{"time":{"updated":"Oct 2, 2024 17:41:39 UTC","updatedISO":"2024-10-02T17:41:39+00:00","updateduk":"Oct 2, 2024 at 18:41 BST"},"disclaimer":"This data was produced from the CoinDesk Bitcoin Price Index (USD). Non-USD currency data converted using hourly conversion rate from openexchangerates.org","chartName":"Bitcoin","bpi":{"USD":{"code":"USD","symbol":"&#36;","rate":"61,455.844","description":"United States Dollar","rate_float":61455.8437},"GBP":{"code":"GBP","symbol":"&pound;","rate":"46,308.084","description":"British Pound Sterling","rate_float":46308.0844},"EUR":{"code":"EUR","symbol":"&euro;","rate":"55,631.059","description":"Euro","rate_float":55631.0588},"CNY":{"code":"CNY","symbol":"&yen;","rate":"432,526.228","description":"Chinese Yuan","rate_float":432526.2277}}}