{"time":{"updated":"May 28, 2024 04:51:13 UTC","updatedISO":"2024-05-28T04:51:13+00:00","updateduk":"May 28, 2024 at 05:51 BST"},"disclaimer":"This data was produced from the CoinDesk Bitcoin Price Index (USD). Non-USD currency data converted using hourly conversion rate from openexchangerates.org","chartName":"Bitcoin","bpi":{"USD":{"code":"USD","symbol":"&#36;","rate":"67,734.798","description":"United States Dollar","rate_float":67734.7975},"GBP":{"code":"GBP","symbol":"&pound;","rate":"52,995.773","description":"British Pound Sterling","rate_float":52995.7733},"EUR":{"code":"EUR","symbol":"&euro;","rate":"62,265.213","description":"Euro","rate_float":62265.2126},"CNY":{"code":"CNY","symbol":"&yen;","rate":"481,343.792","description":"Chinese Yuan","rate_float":481343.7915}}}