{"time":{"updated":"Jun 16, 2024 20:30:39 UTC","updatedISO":"2024-06-16T20:30:39+00:00","updateduk":"Jun 16, 2024 at 21:30 BST"},"disclaimer":"This data was produced from the CoinDesk Bitcoin Price Index (USD). Non-USD currency data converted using hourly conversion rate from openexchangerates.org","chartName":"Bitcoin","bpi":{"USD":{"code":"USD","symbol":"&#36;","rate":"66,619.212","description":"United States Dollar","rate_float":66619.2117},"GBP":{"code":"GBP","symbol":"&pound;","rate":"52,518.123","description":"British Pound Sterling","rate_float":52518.123},"EUR":{"code":"EUR","symbol":"&euro;","rate":"62,243.529","description":"Euro","rate_float":62243.5286},"CNY":{"code":"CNY","symbol":"&yen;","rate":"483,309.057","description":"Chinese Yuan","rate_float":483309.0569}}}