{"time":{"updated":"Sep 18, 2024 15:09:38 UTC","updatedISO":"2024-09-18T15:09:38+00:00","updateduk":"Sep 18, 2024 at 16:09 BST"},"disclaimer":"This data was produced from the CoinDesk Bitcoin Price Index (USD). Non-USD currency data converted using hourly conversion rate from openexchangerates.org","chartName":"Bitcoin","bpi":{"USD":{"code":"USD","symbol":"&#36;","rate":"59,647.766","description":"United States Dollar","rate_float":59647.7661},"GBP":{"code":"GBP","symbol":"&pound;","rate":"45,061.203","description":"British Pound Sterling","rate_float":45061.2031},"EUR":{"code":"EUR","symbol":"&euro;","rate":"53,567.452","description":"Euro","rate_float":53567.4518},"CNY":{"code":"CNY","symbol":"&yen;","rate":"422,288.29","description":"Chinese Yuan","rate_float":422288.2897}}}