{"time":{"updated":"Jul 1, 2024 23:52:11 UTC","updatedISO":"2024-07-01T23:52:11+00:00","updateduk":"Jul 2, 2024 at 00:52 BST"},"disclaimer":"This data was produced from the CoinDesk Bitcoin Price Index (USD). Non-USD currency data converted using hourly conversion rate from openexchangerates.org","chartName":"Bitcoin","bpi":{"USD":{"code":"USD","symbol":"&#36;","rate":"62,839.365","description":"United States Dollar","rate_float":62839.3646},"GBP":{"code":"GBP","symbol":"&pound;","rate":"49,690.668","description":"British Pound Sterling","rate_float":49690.6675},"EUR":{"code":"EUR","symbol":"&euro;","rate":"58,522.992","description":"Euro","rate_float":58522.9915},"CNY":{"code":"CNY","symbol":"&yen;","rate":"456,741.638","description":"Chinese Yuan","rate_float":456741.638}}}