{"time":{"updated":"Sep 19, 2024 08:52:39 UTC","updatedISO":"2024-09-19T08:52:39+00:00","updateduk":"Sep 19, 2024 at 09:52 BST"},"disclaimer":"This data was produced from the CoinDesk Bitcoin Price Index (USD). Non-USD currency data converted using hourly conversion rate from openexchangerates.org","chartName":"Bitcoin","bpi":{"USD":{"code":"USD","symbol":"&#36;","rate":"61,857.723","description":"United States Dollar","rate_float":61857.7231},"GBP":{"code":"GBP","symbol":"&pound;","rate":"46,695.838","description":"British Pound Sterling","rate_float":46695.8384},"EUR":{"code":"EUR","symbol":"&euro;","rate":"55,497.759","description":"Euro","rate_float":55497.7594},"CNY":{"code":"CNY","symbol":"&yen;","rate":"437,346.474","description":"Chinese Yuan","rate_float":437346.4737}}}