{"time":{"updated":"Apr 1, 2022 22:59:00 UTC","updatedISO":"2022-04-01T22:59:00+00:00","updateduk":"Apr 1, 2022 at 23:59 BST"},"disclaimer":"This data was produced from the CoinDesk Bitcoin Price Index (USD). Non-USD currency data converted using hourly conversion rate from openexchangerates.org","chartName":"Bitcoin","bpi":{"USD":{"code":"USD","symbol":"&#36;","rate":"46,375.5868","description":"United States Dollar","rate_float":46375.5868},"GBP":{"code":"GBP","symbol":"&pound;","rate":"35,401.0824","description":"British Pound Sterling","rate_float":35401.0824},"EUR":{"code":"EUR","symbol":"&euro;","rate":"41,986.3694","description":"Euro","rate_float":41986.3694},"CNY":{"code":"CNY","symbol":"&yen;","rate":"40,202.5000","description":"Chinese Yuan","rate_float":40202.5}}}