{"time":{"updated":"Mar 14, 2024 14:42:04 UTC","updatedISO":"2024-03-14T14:42:04+00:00","updateduk":"Mar 14, 2024 at 14:42 GMT"},"disclaimer":"This data was produced from the CoinDesk Bitcoin Price Index (USD). Non-USD currency data converted using hourly conversion rate from openexchangerates.org","chartName":"Bitcoin","bpi":{"USD":{"code":"USD","symbol":"&#36;","rate":"71,819.887","description":"United States Dollar","rate_float":71819.8871},"GBP":{"code":"GBP","symbol":"&pound;","rate":"56,218.238","description":"British Pound Sterling","rate_float":56218.2376},"EUR":{"code":"EUR","symbol":"&euro;","rate":"65,818.043","description":"Euro","rate_float":65818.0428},"CNY":{"code":"CNY","symbol":"&yen;","rate":"516,499.9","description":"Chinese Yuan","rate_float":516499.9001}}}