{"time":{"updated":"May 4, 2024 20:46:28 UTC","updatedISO":"2024-05-04T20:46:28+00:00","updateduk":"May 4, 2024 at 21:46 BST"},"disclaimer":"This data was produced from the CoinDesk Bitcoin Price Index (USD). Non-USD currency data converted using hourly conversion rate from openexchangerates.org","chartName":"Bitcoin","bpi":{"USD":{"code":"USD","symbol":"&#36;","rate":"64,010.423","description":"United States Dollar","rate_float":64010.4231},"GBP":{"code":"GBP","symbol":"&pound;","rate":"51,012.467","description":"British Pound Sterling","rate_float":51012.4666},"EUR":{"code":"EUR","symbol":"&euro;","rate":"59,443.279","description":"Euro","rate_float":59443.2794},"CNY":{"code":"CNY","symbol":"&yen;","rate":"463,262.635","description":"Chinese Yuan","rate_float":463262.635}}}