{"time":{"updated":"Sep 24, 2022 11:06:00 UTC","updatedISO":"2022-09-24T11:06:00+00:00","updateduk":"Sep 24, 2022 at 12:06 BST"},"disclaimer":"This data was produced from the CoinDesk Bitcoin Price Index (USD). Non-USD currency data converted using hourly conversion rate from openexchangerates.org","chartName":"Bitcoin","bpi":{"USD":{"code":"USD","symbol":"&#36;","rate":"19,030.6727","description":"United States Dollar","rate_float":19030.6727},"GBP":{"code":"GBP","symbol":"&pound;","rate":"15,901.8779","description":"British Pound Sterling","rate_float":15901.8779},"EUR":{"code":"EUR","symbol":"&euro;","rate":"18,538.6537","description":"Euro","rate_float":18538.6537},"CNY":{"code":"CNY","symbol":"&yen;","rate":"40,202.5000","description":"Chinese Yuan","rate_float":40202.5}}}