{"time":{"updated":"Sep 2, 2024 11:37:12 UTC","updatedISO":"2024-09-02T11:37:12+00:00","updateduk":"Sep 2, 2024 at 12:37 BST"},"disclaimer":"This data was produced from the CoinDesk Bitcoin Price Index (USD). Non-USD currency data converted using hourly conversion rate from openexchangerates.org","chartName":"Bitcoin","bpi":{"USD":{"code":"USD","symbol":"&#36;","rate":"58,579.427","description":"United States Dollar","rate_float":58579.4267},"GBP":{"code":"GBP","symbol":"&pound;","rate":"44,594.76","description":"British Pound Sterling","rate_float":44594.7602},"EUR":{"code":"EUR","symbol":"&euro;","rate":"52,933.307","description":"Euro","rate_float":52933.3073},"CNY":{"code":"CNY","symbol":"&yen;","rate":"416,663.747","description":"Chinese Yuan","rate_float":416663.7465}}}