{"time":{"updated":"Jul 12, 2024 02:02:18 UTC","updatedISO":"2024-07-12T02:02:18+00:00","updateduk":"Jul 12, 2024 at 03:02 BST"},"disclaimer":"This data was produced from the CoinDesk Bitcoin Price Index (USD). Non-USD currency data converted using hourly conversion rate from openexchangerates.org","chartName":"Bitcoin","bpi":{"USD":{"code":"USD","symbol":"&#36;","rate":"56,961.036","description":"United States Dollar","rate_float":56961.0358},"GBP":{"code":"GBP","symbol":"&pound;","rate":"44,124.582","description":"British Pound Sterling","rate_float":44124.5816},"EUR":{"code":"EUR","symbol":"&euro;","rate":"52,402.786","description":"Euro","rate_float":52402.7859},"CNY":{"code":"CNY","symbol":"&yen;","rate":"413,286.491","description":"Chinese Yuan","rate_float":413286.4913}}}