{"time":{"updated":"Jan 26, 2024 05:10:13 UTC","updatedISO":"2024-01-26T05:10:13+00:00","updateduk":"Jan 26, 2024 at 05:10 GMT"},"disclaimer":"This data was produced from the CoinDesk Bitcoin Price Index (USD). Non-USD currency data converted using hourly conversion rate from openexchangerates.org","chartName":"Bitcoin","bpi":{"USD":{"code":"USD","symbol":"&#36;","rate":"40,171.352","description":"United States Dollar","rate_float":40171.3519},"GBP":{"code":"GBP","symbol":"&pound;","rate":"31,603.485","description":"British Pound Sterling","rate_float":31603.4854},"EUR":{"code":"EUR","symbol":"&euro;","rate":"37,041.441","description":"Euro","rate_float":37041.4412},"CNY":{"code":"CNY","symbol":"&yen;","rate":"285,178.436","description":"Chinese Yuan","rate_float":285178.4355}}}