{"time":{"updated":"Nov 11, 2022 10:32:00 UTC","updatedISO":"2022-11-11T10:32:00+00:00","updateduk":"Nov 11, 2022 at 10:32 GMT"},"disclaimer":"This data was produced from the CoinDesk Bitcoin Price Index (USD). Non-USD currency data converted using hourly conversion rate from openexchangerates.org","chartName":"Bitcoin","bpi":{"USD":{"code":"USD","symbol":"&#36;","rate":"17,286.9876","description":"United States Dollar","rate_float":17286.9876},"GBP":{"code":"GBP","symbol":"&pound;","rate":"14,444.8686","description":"British Pound Sterling","rate_float":14444.8686},"EUR":{"code":"EUR","symbol":"&euro;","rate":"16,840.0498","description":"Euro","rate_float":16840.0498},"CNY":{"code":"CNY","symbol":"&yen;","rate":"40,202.5000","description":"Chinese Yuan","rate_float":40202.5}}}