{"time":{"updated":"Oct 1, 2021 22:02:00 UTC","updatedISO":"2021-10-01T22:02:00+00:00","updateduk":"Oct 1, 2021 at 23:02 BST"},"disclaimer":"This data was produced from the CoinDesk Bitcoin Price Index (USD). Non-USD currency data converted using hourly conversion rate from openexchangerates.org","chartName":"Bitcoin","bpi":{"USD":{"code":"USD","symbol":"&#36;","rate":"48,296.8537","description":"United States Dollar","rate_float":48296.8537},"GBP":{"code":"GBP","symbol":"&pound;","rate":"35,653.9448","description":"British Pound Sterling","rate_float":35653.9448},"EUR":{"code":"EUR","symbol":"&euro;","rate":"41,649.5645","description":"Euro","rate_float":41649.5645},"CNY":{"code":"CNY","symbol":"&yen;","rate":"40,202.5000","description":"Chinese Yuan","rate_float":40202.5}}}