{"time":{"updated":"Sep 18, 2024 09:09:14 UTC","updatedISO":"2024-09-18T09:09:14+00:00","updateduk":"Sep 18, 2024 at 10:09 BST"},"disclaimer":"This data was produced from the CoinDesk Bitcoin Price Index (USD). Non-USD currency data converted using hourly conversion rate from openexchangerates.org","chartName":"Bitcoin","bpi":{"USD":{"code":"USD","symbol":"&#36;","rate":"60,063.743","description":"United States Dollar","rate_float":60063.7429},"GBP":{"code":"GBP","symbol":"&pound;","rate":"45,510.358","description":"British Pound Sterling","rate_float":45510.3581},"EUR":{"code":"EUR","symbol":"&euro;","rate":"53,960.366","description":"Euro","rate_float":53960.3657},"CNY":{"code":"CNY","symbol":"&yen;","rate":"425,893.982","description":"Chinese Yuan","rate_float":425893.9819}}}