{"time":{"updated":"Aug 7, 2021 00:31:00 UTC","updatedISO":"2021-08-07T00:31:00+00:00","updateduk":"Aug 7, 2021 at 01:31 BST"},"disclaimer":"This data was produced from the CoinDesk Bitcoin Price Index (USD). Non-USD currency data converted using hourly conversion rate from openexchangerates.org","chartName":"Bitcoin","bpi":{"USD":{"code":"USD","symbol":"&#36;","rate":"42,784.5501","description":"United States Dollar","rate_float":42784.5501},"GBP":{"code":"GBP","symbol":"&pound;","rate":"30,835.6382","description":"British Pound Sterling","rate_float":30835.6382},"EUR":{"code":"EUR","symbol":"&euro;","rate":"36,372.7719","description":"Euro","rate_float":36372.7719},"CNY":{"code":"CNY","symbol":"&yen;","rate":"40,202.5000","description":"Chinese Yuan","rate_float":40202.5}}}