{"time":{"updated":"Dec 5, 2024 04:48:57 UTC","updatedISO":"2024-12-05T04:48:57+00:00","updateduk":"Dec 5, 2024 at 04:48 GMT"},"disclaimer":"This data was produced from the CoinDesk Bitcoin Price Index (USD). Non-USD currency data converted using hourly conversion rate from openexchangerates.org","chartName":"Bitcoin","bpi":{"USD":{"code":"USD","symbol":"&#36;","rate":"103,074.507","description":"United States Dollar","rate_float":103074.507},"GBP":{"code":"GBP","symbol":"&pound;","rate":"81,101.805","description":"British Pound Sterling","rate_float":81101.8051},"EUR":{"code":"EUR","symbol":"&euro;","rate":"97,951.704","description":"Euro","rate_float":97951.704},"CNY":{"code":"CNY","symbol":"&yen;","rate":"749,392.896","description":"Chinese Yuan","rate_float":749392.8959}}}