{"time":{"updated":"Jan 18, 2025 15:48:14 UTC","updatedISO":"2025-01-18T15:48:14+00:00","updateduk":"Jan 18, 2025 at 15:48 GMT"},"disclaimer":"This data was produced from the CoinDesk Bitcoin Price Index (USD). Non-USD currency data converted using hourly conversion rate from openexchangerates.org","chartName":"Bitcoin","bpi":{"USD":{"code":"USD","symbol":"&#36;","rate":"105,710.7","description":"United States Dollar","rate_float":105710.6997},"GBP":{"code":"GBP","symbol":"&pound;","rate":"84,312.211","description":"British Pound Sterling","rate_float":84312.2114},"EUR":{"code":"EUR","symbol":"&euro;","rate":"101,665.574","description":"Euro","rate_float":101665.5741},"CNY":{"code":"CNY","symbol":"&yen;","rate":"774,637.437","description":"Chinese Yuan","rate_float":774637.4367}}}