{"time":{"updated":"Oct 17, 2024 22:48:50 UTC","updatedISO":"2024-10-17T22:48:50+00:00","updateduk":"Oct 17, 2024 at 23:48 BST"},"disclaimer":"This data was produced from the CoinDesk Bitcoin Price Index (USD). Non-USD currency data converted using hourly conversion rate from openexchangerates.org","chartName":"Bitcoin","bpi":{"USD":{"code":"USD","symbol":"&#36;","rate":"67,360.613","description":"United States Dollar","rate_float":67360.6126},"GBP":{"code":"GBP","symbol":"&pound;","rate":"51,762.724","description":"British Pound Sterling","rate_float":51762.7238},"EUR":{"code":"EUR","symbol":"&euro;","rate":"62,185.566","description":"Euro","rate_float":62185.5661},"CNY":{"code":"CNY","symbol":"&yen;","rate":"479,877.004","description":"Chinese Yuan","rate_float":479877.0039}}}