{"time":{"updated":"Apr 12, 2024 03:58:28 UTC","updatedISO":"2024-04-12T03:58:28+00:00","updateduk":"Apr 12, 2024 at 04:58 BST"},"disclaimer":"This data was produced from the CoinDesk Bitcoin Price Index (USD). Non-USD currency data converted using hourly conversion rate from openexchangerates.org","chartName":"Bitcoin","bpi":{"USD":{"code":"USD","symbol":"&#36;","rate":"70,982.466","description":"United States Dollar","rate_float":70982.4664},"GBP":{"code":"GBP","symbol":"&pound;","rate":"56,527.597","description":"British Pound Sterling","rate_float":56527.5969},"EUR":{"code":"EUR","symbol":"&euro;","rate":"66,173.333","description":"Euro","rate_float":66173.3333},"CNY":{"code":"CNY","symbol":"&yen;","rate":"513,650.421","description":"Chinese Yuan","rate_float":513650.4213}}}