{"time":{"updated":"Sep 14, 2024 10:59:23 UTC","updatedISO":"2024-09-14T10:59:23+00:00","updateduk":"Sep 14, 2024 at 11:59 BST"},"disclaimer":"This data was produced from the CoinDesk Bitcoin Price Index (USD). Non-USD currency data converted using hourly conversion rate from openexchangerates.org","chartName":"Bitcoin","bpi":{"USD":{"code":"USD","symbol":"&#36;","rate":"59,879.599","description":"United States Dollar","rate_float":59879.5991},"GBP":{"code":"GBP","symbol":"&pound;","rate":"45,629.512","description":"British Pound Sterling","rate_float":45629.512},"EUR":{"code":"EUR","symbol":"&euro;","rate":"54,011.279","description":"Euro","rate_float":54011.2786},"CNY":{"code":"CNY","symbol":"&yen;","rate":"424,755.936","description":"Chinese Yuan","rate_float":424755.9359}}}