{"time":{"updated":"Nov 4, 2024 19:10:35 UTC","updatedISO":"2024-11-04T19:10:35+00:00","updateduk":"Nov 4, 2024 at 19:10 GMT"},"disclaimer":"This data was produced from the CoinDesk Bitcoin Price Index (USD). Non-USD currency data converted using hourly conversion rate from openexchangerates.org","chartName":"Bitcoin","bpi":{"USD":{"code":"USD","symbol":"&#36;","rate":"68,029.92","description":"United States Dollar","rate_float":68029.9196},"GBP":{"code":"GBP","symbol":"&pound;","rate":"52,505.016","description":"British Pound Sterling","rate_float":52505.0158},"EUR":{"code":"EUR","symbol":"&euro;","rate":"62,477.25","description":"Euro","rate_float":62477.2496},"CNY":{"code":"CNY","symbol":"&yen;","rate":"482,971.612","description":"Chinese Yuan","rate_float":482971.6115}}}