{"time":{"updated":"Jul 8, 2024 19:06:59 UTC","updatedISO":"2024-07-08T19:06:59+00:00","updateduk":"Jul 8, 2024 at 20:06 BST"},"disclaimer":"This data was produced from the CoinDesk Bitcoin Price Index (USD). Non-USD currency data converted using hourly conversion rate from openexchangerates.org","chartName":"Bitcoin","bpi":{"USD":{"code":"USD","symbol":"&#36;","rate":"56,324.188","description":"United States Dollar","rate_float":56324.188},"GBP":{"code":"GBP","symbol":"&pound;","rate":"43,942.442","description":"British Pound Sterling","rate_float":43942.4417},"EUR":{"code":"EUR","symbol":"&euro;","rate":"51,997.42","description":"Euro","rate_float":51997.4202},"CNY":{"code":"CNY","symbol":"&yen;","rate":"409,369.831","description":"Chinese Yuan","rate_float":409369.8306}}}