{"time":{"updated":"Mar 14, 2024 10:53:30 UTC","updatedISO":"2024-03-14T10:53:30+00:00","updateduk":"Mar 14, 2024 at 10:53 GMT"},"disclaimer":"This data was produced from the CoinDesk Bitcoin Price Index (USD). Non-USD currency data converted using hourly conversion rate from openexchangerates.org","chartName":"Bitcoin","bpi":{"USD":{"code":"USD","symbol":"&#36;","rate":"73,057.027","description":"United States Dollar","rate_float":73057.0272},"GBP":{"code":"GBP","symbol":"&pound;","rate":"57,005.083","description":"British Pound Sterling","rate_float":57005.0833},"EUR":{"code":"EUR","symbol":"&euro;","rate":"66,773.027","description":"Euro","rate_float":66773.027},"CNY":{"code":"CNY","symbol":"&yen;","rate":"525,221.58","description":"Chinese Yuan","rate_float":525221.58}}}