{"time":{"updated":"Dec 24, 2024 05:37:54 UTC","updatedISO":"2024-12-24T05:37:54+00:00","updateduk":"Dec 24, 2024 at 05:37 GMT"},"disclaimer":"This data was produced from the CoinDesk Bitcoin Price Index (USD). Non-USD currency data converted using hourly conversion rate from openexchangerates.org","chartName":"Bitcoin","bpi":{"USD":{"code":"USD","symbol":"&#36;","rate":"94,480.716","description":"United States Dollar","rate_float":94480.716},"GBP":{"code":"GBP","symbol":"&pound;","rate":"75,366.417","description":"British Pound Sterling","rate_float":75366.4168},"EUR":{"code":"EUR","symbol":"&euro;","rate":"90,791.622","description":"Euro","rate_float":90791.6219},"CNY":{"code":"CNY","symbol":"&yen;","rate":"689,548.609","description":"Chinese Yuan","rate_float":689548.6094}}}