{"time":{"updated":"Jun 10, 2024 17:25:31 UTC","updatedISO":"2024-06-10T17:25:31+00:00","updateduk":"Jun 10, 2024 at 18:25 BST"},"disclaimer":"This data was produced from the CoinDesk Bitcoin Price Index (USD). Non-USD currency data converted using hourly conversion rate from openexchangerates.org","chartName":"Bitcoin","bpi":{"USD":{"code":"USD","symbol":"&#36;","rate":"69,933.842","description":"United States Dollar","rate_float":69933.8422},"GBP":{"code":"GBP","symbol":"&pound;","rate":"54,939.537","description":"British Pound Sterling","rate_float":54939.5369},"EUR":{"code":"EUR","symbol":"&euro;","rate":"65,029.172","description":"Euro","rate_float":65029.1721},"CNY":{"code":"CNY","symbol":"&yen;","rate":"497,145.698","description":"Chinese Yuan","rate_float":497145.6975}}}