{"time":{"updated":"Nov 8, 2021 13:57:00 UTC","updatedISO":"2021-11-08T13:57:00+00:00","updateduk":"Nov 8, 2021 at 13:57 GMT"},"disclaimer":"This data was produced from the CoinDesk Bitcoin Price Index (USD). Non-USD currency data converted using hourly conversion rate from openexchangerates.org","chartName":"Bitcoin","bpi":{"USD":{"code":"USD","symbol":"&#36;","rate":"65,400.8765","description":"United States Dollar","rate_float":65400.8765},"GBP":{"code":"GBP","symbol":"&pound;","rate":"48,343.4123","description":"British Pound Sterling","rate_float":48343.4123},"EUR":{"code":"EUR","symbol":"&euro;","rate":"56,494.2582","description":"Euro","rate_float":56494.2582},"CNY":{"code":"CNY","symbol":"&yen;","rate":"40,202.5000","description":"Chinese Yuan","rate_float":40202.5}}}