{"time":{"updated":"Mar 5, 2024 20:20:02 UTC","updatedISO":"2024-03-05T20:20:02+00:00","updateduk":"Mar 5, 2024 at 20:20 GMT"},"disclaimer":"This data was produced from the CoinDesk Bitcoin Price Index (USD). Non-USD currency data converted using hourly conversion rate from openexchangerates.org","chartName":"Bitcoin","bpi":{"USD":{"code":"USD","symbol":"&#36;","rate":"62,491.609","description":"United States Dollar","rate_float":62491.6094},"GBP":{"code":"GBP","symbol":"&pound;","rate":"49,197.644","description":"British Pound Sterling","rate_float":49197.6443},"EUR":{"code":"EUR","symbol":"&euro;","rate":"57,580.831","description":"Euro","rate_float":57580.8312},"CNY":{"code":"CNY","symbol":"&yen;","rate":"449,745.863","description":"Chinese Yuan","rate_float":449745.8634}}}