{"time":{"updated":"Nov 6, 2024 14:13:21 UTC","updatedISO":"2024-11-06T14:13:21+00:00","updateduk":"Nov 6, 2024 at 14:13 GMT"},"disclaimer":"This data was produced from the CoinDesk Bitcoin Price Index (USD). Non-USD currency data converted using hourly conversion rate from openexchangerates.org","chartName":"Bitcoin","bpi":{"USD":{"code":"USD","symbol":"&#36;","rate":"73,637.25","description":"United States Dollar","rate_float":73637.2503},"GBP":{"code":"GBP","symbol":"&pound;","rate":"57,290.738","description":"British Pound Sterling","rate_float":57290.738},"EUR":{"code":"EUR","symbol":"&euro;","rate":"68,896.631","description":"Euro","rate_float":68896.6314},"CNY":{"code":"CNY","symbol":"&yen;","rate":"528,641.82","description":"Chinese Yuan","rate_float":528641.8198}}}