{"time":{"updated":"Jul 18, 2024 20:00:37 UTC","updatedISO":"2024-07-18T20:00:37+00:00","updateduk":"Jul 18, 2024 at 21:00 BST"},"disclaimer":"This data was produced from the CoinDesk Bitcoin Price Index (USD). Non-USD currency data converted using hourly conversion rate from openexchangerates.org","chartName":"Bitcoin","bpi":{"USD":{"code":"USD","symbol":"&#36;","rate":"63,555.881","description":"United States Dollar","rate_float":63555.881},"GBP":{"code":"GBP","symbol":"&pound;","rate":"49,083.826","description":"British Pound Sterling","rate_float":49083.8255},"EUR":{"code":"EUR","symbol":"&euro;","rate":"58,313.856","description":"Euro","rate_float":58313.8555},"CNY":{"code":"CNY","symbol":"&yen;","rate":"461,453.829","description":"Chinese Yuan","rate_float":461453.8294}}}