{"time":{"updated":"Jul 31, 2024 14:29:30 UTC","updatedISO":"2024-07-31T14:29:30+00:00","updateduk":"Jul 31, 2024 at 15:29 BST"},"disclaimer":"This data was produced from the CoinDesk Bitcoin Price Index (USD). Non-USD currency data converted using hourly conversion rate from openexchangerates.org","chartName":"Bitcoin","bpi":{"USD":{"code":"USD","symbol":"&#36;","rate":"66,149.679","description":"United States Dollar","rate_float":66149.6791},"GBP":{"code":"GBP","symbol":"&pound;","rate":"51,516.444","description":"British Pound Sterling","rate_float":51516.444},"EUR":{"code":"EUR","symbol":"&euro;","rate":"61,008.129","description":"Euro","rate_float":61008.1292},"CNY":{"code":"CNY","symbol":"&yen;","rate":"477,547.764","description":"Chinese Yuan","rate_float":477547.7636}}}