{"time":{"updated":"Jan 29, 2024 11:21:45 UTC","updatedISO":"2024-01-29T11:21:45+00:00","updateduk":"Jan 29, 2024 at 11:21 GMT"},"disclaimer":"This data was produced from the CoinDesk Bitcoin Price Index (USD). Non-USD currency data converted using hourly conversion rate from openexchangerates.org","chartName":"Bitcoin","bpi":{"USD":{"code":"USD","symbol":"&#36;","rate":"42,343.075","description":"United States Dollar","rate_float":42343.0754},"GBP":{"code":"GBP","symbol":"&pound;","rate":"33,332.173","description":"British Pound Sterling","rate_float":33332.1725},"EUR":{"code":"EUR","symbol":"&euro;","rate":"39,115.093","description":"Euro","rate_float":39115.0933},"CNY":{"code":"CNY","symbol":"&yen;","rate":"304,078.327","description":"Chinese Yuan","rate_float":304078.327}}}