{"time":{"updated":"Jul 18, 2024 23:33:45 UTC","updatedISO":"2024-07-18T23:33:45+00:00","updateduk":"Jul 19, 2024 at 00:33 BST"},"disclaimer":"This data was produced from the CoinDesk Bitcoin Price Index (USD). Non-USD currency data converted using hourly conversion rate from openexchangerates.org","chartName":"Bitcoin","bpi":{"USD":{"code":"USD","symbol":"&#36;","rate":"64,031.958","description":"United States Dollar","rate_float":64031.9582},"GBP":{"code":"GBP","symbol":"&pound;","rate":"49,465.968","description":"British Pound Sterling","rate_float":49465.9684},"EUR":{"code":"EUR","symbol":"&euro;","rate":"58,757.838","description":"Euro","rate_float":58757.8379},"CNY":{"code":"CNY","symbol":"&yen;","rate":"464,846.404","description":"Chinese Yuan","rate_float":464846.4039}}}