{"time":{"updated":"Jul 4, 2024 23:35:50 UTC","updatedISO":"2024-07-04T23:35:50+00:00","updateduk":"Jul 5, 2024 at 00:35 BST"},"disclaimer":"This data was produced from the CoinDesk Bitcoin Price Index (USD). Non-USD currency data converted using hourly conversion rate from openexchangerates.org","chartName":"Bitcoin","bpi":{"USD":{"code":"USD","symbol":"&#36;","rate":"57,770.226","description":"United States Dollar","rate_float":57770.2264},"GBP":{"code":"GBP","symbol":"&pound;","rate":"45,284.347","description":"British Pound Sterling","rate_float":45284.3474},"EUR":{"code":"EUR","symbol":"&euro;","rate":"53,428.794","description":"Euro","rate_float":53428.7939},"CNY":{"code":"CNY","symbol":"&yen;","rate":"419,827.79","description":"Chinese Yuan","rate_float":419827.7896}}}