{"time":{"updated":"Jan 24, 2025 11:52:50 UTC","updatedISO":"2025-01-24T11:52:50+00:00","updateduk":"Jan 24, 2025 at 11:52 GMT"},"disclaimer":"This data was produced from the CoinDesk Bitcoin Price Index (USD). Non-USD currency data converted using hourly conversion rate from openexchangerates.org","chartName":"Bitcoin","bpi":{"USD":{"code":"USD","symbol":"&#36;","rate":"104,641.862","description":"United States Dollar","rate_float":104641.862},"GBP":{"code":"GBP","symbol":"&pound;","rate":"83,459.733","description":"British Pound Sterling","rate_float":83459.733},"EUR":{"code":"EUR","symbol":"&euro;","rate":"100,637.637","description":"Euro","rate_float":100637.6365},"CNY":{"code":"CNY","symbol":"&yen;","rate":"766,805.1","description":"Chinese Yuan","rate_float":766805.1002}}}