{"time":{"updated":"Jan 2, 2025 04:48:58 UTC","updatedISO":"2025-01-02T04:48:58+00:00","updateduk":"Jan 2, 2025 at 04:48 GMT"},"disclaimer":"This data was produced from the CoinDesk Bitcoin Price Index (USD). Non-USD currency data converted using hourly conversion rate from openexchangerates.org","chartName":"Bitcoin","bpi":{"USD":{"code":"USD","symbol":"&#36;","rate":"96,265.133","description":"United States Dollar","rate_float":96265.1331},"GBP":{"code":"GBP","symbol":"&pound;","rate":"76,769.518","description":"British Pound Sterling","rate_float":76769.5184},"EUR":{"code":"EUR","symbol":"&euro;","rate":"92,353.977","description":"Euro","rate_float":92353.977},"CNY":{"code":"CNY","symbol":"&yen;","rate":"702,600.701","description":"Chinese Yuan","rate_float":702600.7006}}}