{"time":{"updated":"Dec 30, 2023 09:18:00 UTC","updatedISO":"2023-12-30T09:18:00+00:00","updateduk":"Dec 30, 2023 at 09:18 GMT"},"disclaimer":"This data was produced from the CoinDesk Bitcoin Price Index (USD). Non-USD currency data converted using hourly conversion rate from openexchangerates.org","chartName":"Bitcoin","bpi":{"USD":{"code":"USD","symbol":"&#36;","rate":"41,582.7564","description":"United States Dollar","rate_float":41582.7564},"GBP":{"code":"GBP","symbol":"&pound;","rate":"34,746.2186","description":"British Pound Sterling","rate_float":34746.2186},"EUR":{"code":"EUR","symbol":"&euro;","rate":"40,507.6759","description":"Euro","rate_float":40507.6759},"CNY":{"code":"CNY","symbol":"&yen;","rate":"40,202.5000","description":"Chinese Yuan","rate_float":40202.5}}}