{"time":{"updated":"May 28, 2024 23:44:31 UTC","updatedISO":"2024-05-28T23:44:31+00:00","updateduk":"May 29, 2024 at 00:44 BST"},"disclaimer":"This data was produced from the CoinDesk Bitcoin Price Index (USD). Non-USD currency data converted using hourly conversion rate from openexchangerates.org","chartName":"Bitcoin","bpi":{"USD":{"code":"USD","symbol":"&#36;","rate":"68,395.462","description":"United States Dollar","rate_float":68395.462},"GBP":{"code":"GBP","symbol":"&pound;","rate":"53,601.318","description":"British Pound Sterling","rate_float":53601.3184},"EUR":{"code":"EUR","symbol":"&euro;","rate":"62,998.445","description":"Euro","rate_float":62998.4445},"CNY":{"code":"CNY","symbol":"&yen;","rate":"486,360.13","description":"Chinese Yuan","rate_float":486360.1302}}}