{"time":{"updated":"May 16, 2024 07:10:27 UTC","updatedISO":"2024-05-16T07:10:27+00:00","updateduk":"May 16, 2024 at 08:10 BST"},"disclaimer":"This data was produced from the CoinDesk Bitcoin Price Index (USD). Non-USD currency data converted using hourly conversion rate from openexchangerates.org","chartName":"Bitcoin","bpi":{"USD":{"code":"USD","symbol":"&#36;","rate":"66,050.715","description":"United States Dollar","rate_float":66050.7148},"GBP":{"code":"GBP","symbol":"&pound;","rate":"52,080.13","description":"British Pound Sterling","rate_float":52080.13},"EUR":{"code":"EUR","symbol":"&euro;","rate":"60,711.77","description":"Euro","rate_float":60711.7695},"CNY":{"code":"CNY","symbol":"&yen;","rate":"476,628.563","description":"Chinese Yuan","rate_float":476628.5634}}}