{"time":{"updated":"Aug 29, 2021 03:35:00 UTC","updatedISO":"2021-08-29T03:35:00+00:00","updateduk":"Aug 29, 2021 at 04:35 BST"},"disclaimer":"This data was produced from the CoinDesk Bitcoin Price Index (USD). Non-USD currency data converted using hourly conversion rate from openexchangerates.org","chartName":"Bitcoin","bpi":{"USD":{"code":"USD","symbol":"&#36;","rate":"48,334.1333","description":"United States Dollar","rate_float":48334.1333},"GBP":{"code":"GBP","symbol":"&pound;","rate":"35,113.7812","description":"British Pound Sterling","rate_float":35113.7812},"EUR":{"code":"EUR","symbol":"&euro;","rate":"40,977.0982","description":"Euro","rate_float":40977.0982},"CNY":{"code":"CNY","symbol":"&yen;","rate":"40,202.5000","description":"Chinese Yuan","rate_float":40202.5}}}