{"time":{"updated":"Jan 31, 2024 04:30:26 UTC","updatedISO":"2024-01-31T04:30:26+00:00","updateduk":"Jan 31, 2024 at 04:30 GMT"},"disclaimer":"This data was produced from the CoinDesk Bitcoin Price Index (USD). Non-USD currency data converted using hourly conversion rate from openexchangerates.org","chartName":"Bitcoin","bpi":{"USD":{"code":"USD","symbol":"&#36;","rate":"42,943.66","description":"United States Dollar","rate_float":42943.6602},"GBP":{"code":"GBP","symbol":"&pound;","rate":"33,876.235","description":"British Pound Sterling","rate_float":33876.2352},"EUR":{"code":"EUR","symbol":"&euro;","rate":"39,694.114","description":"Euro","rate_float":39694.1135},"CNY":{"code":"CNY","symbol":"&yen;","rate":"304,590.793","description":"Chinese Yuan","rate_float":304590.7933}}}