{"time":{"updated":"Nov 19, 2021 20:28:00 UTC","updatedISO":"2021-11-19T20:28:00+00:00","updateduk":"Nov 19, 2021 at 20:28 GMT"},"disclaimer":"This data was produced from the CoinDesk Bitcoin Price Index (USD). Non-USD currency data converted using hourly conversion rate from openexchangerates.org","chartName":"Bitcoin","bpi":{"USD":{"code":"USD","symbol":"&#36;","rate":"57,842.0279","description":"United States Dollar","rate_float":57842.0279},"GBP":{"code":"GBP","symbol":"&pound;","rate":"43,015.1495","description":"British Pound Sterling","rate_float":43015.1495},"EUR":{"code":"EUR","symbol":"&euro;","rate":"51,235.6006","description":"Euro","rate_float":51235.6006},"CNY":{"code":"CNY","symbol":"&yen;","rate":"40,202.5000","description":"Chinese Yuan","rate_float":40202.5}}}