{"time":{"updated":"Dec 31, 2024 11:50:04 UTC","updatedISO":"2024-12-31T11:50:04+00:00","updateduk":"Dec 31, 2024 at 11:50 GMT"},"disclaimer":"This data was produced from the CoinDesk Bitcoin Price Index (USD). Non-USD currency data converted using hourly conversion rate from openexchangerates.org","chartName":"Bitcoin","bpi":{"USD":{"code":"USD","symbol":"&#36;","rate":"94,265.239","description":"United States Dollar","rate_float":94265.2386},"GBP":{"code":"GBP","symbol":"&pound;","rate":"75,174.643","description":"British Pound Sterling","rate_float":75174.6425},"EUR":{"code":"EUR","symbol":"&euro;","rate":"90,435.336","description":"Euro","rate_float":90435.3362},"CNY":{"code":"CNY","symbol":"&yen;","rate":"688,004.271","description":"Chinese Yuan","rate_float":688004.2705}}}