{"time":{"updated":"Apr 15, 2023 21:44:00 UTC","updatedISO":"2023-04-15T21:44:00+00:00","updateduk":"Apr 15, 2023 at 22:44 BST"},"disclaimer":"This data was produced from the CoinDesk Bitcoin Price Index (USD). Non-USD currency data converted using hourly conversion rate from openexchangerates.org","chartName":"Bitcoin","bpi":{"USD":{"code":"USD","symbol":"&#36;","rate":"30,365.2933","description":"United States Dollar","rate_float":30365.2933},"GBP":{"code":"GBP","symbol":"&pound;","rate":"25,372.9961","description":"British Pound Sterling","rate_float":25372.9961},"EUR":{"code":"EUR","symbol":"&euro;","rate":"29,580.2290","description":"Euro","rate_float":29580.229},"CNY":{"code":"CNY","symbol":"&yen;","rate":"40,202.5000","description":"Chinese Yuan","rate_float":40202.5}}}