{"time":{"updated":"Sep 20, 2024 15:50:22 UTC","updatedISO":"2024-09-20T15:50:22+00:00","updateduk":"Sep 20, 2024 at 16:50 BST"},"disclaimer":"This data was produced from the CoinDesk Bitcoin Price Index (USD). Non-USD currency data converted using hourly conversion rate from openexchangerates.org","chartName":"Bitcoin","bpi":{"USD":{"code":"USD","symbol":"&#36;","rate":"63,261.979","description":"United States Dollar","rate_float":63261.9794},"GBP":{"code":"GBP","symbol":"&pound;","rate":"47,634.183","description":"British Pound Sterling","rate_float":47634.1829},"EUR":{"code":"EUR","symbol":"&euro;","rate":"56,767.758","description":"Euro","rate_float":56767.7577},"CNY":{"code":"CNY","symbol":"&yen;","rate":"446,243.677","description":"Chinese Yuan","rate_float":446243.6766}}}